nbdoc/__init__.py
nbdoc/_nbdev.py
nbdoc/convert.py
nbdoc/docindex.py
nbdoc/mdx.py
nbdoc/media.py
nbdoc/run.py
nbdoc/showdoc.py
nbdoc/test_utils.py
nbdoc/templates/ob.tpl
nbdoc-0.0.79.dist-info/LICENSE
nbdoc-0.0.79.dist-info/METADATA
nbdoc-0.0.79.dist-info/WHEEL
nbdoc-0.0.79.dist-info/entry_points.txt
nbdoc-0.0.79.dist-info/top_level.txt
nbdoc-0.0.79.dist-info/RECORD
