Metadata-Version: 2.1
Name: nbdoc
Version: 0.0.79
Summary: Generate beautiful, testable documentation with Jupyter Notebooks
Home-page: https://github.com/outerbounds/nbdoc/tree/master/
Author: Hamel Husain
Author-email: hamel@outerbounds.com
License: Apache Software License 2.0
Keywords: documentation python jupyter notebook
Platform: UNKNOWN
Classifier: Development Status :: 3 - Alpha
Classifier: Intended Audience :: Developers
Classifier: Natural Language :: English
Classifier: Programming Language :: Python :: 3.8
Classifier: License :: OSI Approved :: Apache Software License
Requires-Python: >=3.8
License-File: LICENSE
Requires-Dist: pip
Requires-Dist: packaging
Requires-Dist: nbconvert (>=6.4.1)
Requires-Dist: nbdev (==1.2.0)
Requires-Dist: fastcore (==1.4.2)
Requires-Dist: numpydoc (==1.2)
Requires-Dist: black[jupyter] (>=22.1.0)
Provides-Extra: dev
